Unleashed/Unleashed.py
Unleashed/__init__.py
Unleashed-0.2.3.dist-info/LICENSE
Unleashed-0.2.3.dist-info/METADATA
Unleashed-0.2.3.dist-info/WHEEL
Unleashed-0.2.3.dist-info/top_level.txt
Unleashed-0.2.3.dist-info/RECORD
