Metadata-Version: 2.1
Name: Unleashed
Version: 0.2.3
Summary: A Python library to interact with the Unleashed API.
Home-page: https://github.com/ejedev/Unleashed
Author: ejedev
Author-email: ev3098@gmail.com
License: MIT
Download-URL: https://github.com/ejedev/Unleashed/archive/v0.2.3.tar.gz
Keywords: Unleashed,API
Platform: UNKNOWN
Classifier: Development Status :: 3 - Alpha
Classifier: Intended Audience :: Developers
Classifier: Topic :: Software Development :: Build Tools
Classifier: License :: OSI Approved :: MIT License
Classifier: Programming Language :: Python :: 3.6
Classifier: Programming Language :: Python :: 3.7
Classifier: Programming Language :: Python :: 3.8
Requires-Dist: wheel
